torch2coreml/__init__.py
torch2coreml/_layers.py
torch2coreml/_torch_converter.py
torch2coreml/_utils.py
torch2coreml-0.2.0.dist-info/DESCRIPTION.rst
torch2coreml-0.2.0.dist-info/METADATA
torch2coreml-0.2.0.dist-info/RECORD
torch2coreml-0.2.0.dist-info/WHEEL
torch2coreml-0.2.0.dist-info/metadata.json
torch2coreml-0.2.0.dist-info/top_level.txt
