Metadata-Version: 2.0
Name: torch2coreml
Version: 0.2.0
Summary: Convert Torch7 models into Apple CoreML format.
Home-page: https://github.com/prisma-ai/torch2coreml/
Author: Oleg Poyaganov
Author-email: oleg@prisma-ai.com
License: MIT
Keywords: coreml machinelearning ml coremltools torch converter neural
Platform: UNKNOWN
Classifier: Development Status :: 4 - Beta
Classifier: License :: OSI Approved :: MIT License
Classifier: Intended Audience :: Developers
Classifier: Intended Audience :: End Users/Desktop
Classifier: Operating System :: MacOS :: MacOS X
Classifier: Programming Language :: Python :: 2.7
Classifier: Topic :: Scientific/Engineering
Classifier: Topic :: Software Development
Requires-Python: ==2.7.*
Requires-Dist: coremltools (>=0.6.2)
Requires-Dist: torch
